altdeutsch/__init__.py
altdeutsch/reader.py
altdeutsch/tests/__init__.py
altdeutsch/tests/test_reader.py
altdeutsch/tests/data/hildebrandslied.txt
altdeutsch-1.0.1.dist-info/LICENSE
altdeutsch-1.0.1.dist-info/METADATA
altdeutsch-1.0.1.dist-info/WHEEL
altdeutsch-1.0.1.dist-info/top_level.txt
altdeutsch-1.0.1.dist-info/zip-safe
altdeutsch-1.0.1.dist-info/RECORD
