Metadata-Version: 2.1
Name: altdeutsch
Version: 1.0.1
Summary: Parse Referenzkorpus Altdeutsch
Home-page: https://github.com/clemsciences/old_high_german_texts
Author: Clément Besnier
Author-email: clemsciences@aol.com
License: License :: OSI Approved :: MIT License
Platform: UNKNOWN
Classifier: Programming Language :: Python
Requires-Python: >=3.6
